{
  "timestamp": "2025-04-15 15:28:02.375956+00:00",
  "nodes": [
    {
      "id": "SAT_1",
      "x": -4923.896484375,
      "y": 4116.921875,
      "z": 3062.466064453125
    },
    {
      "id": "SAT_2",
      "x": -6580.69677734375,
      "y": 390.09368896484375,
      "z": -3127.97265625
    },
    {
      "id": "SAT_3",
      "x": -7362.7978515625,
      "y": -962.018798828125,
      "z": -297.6509704589844
    },
    {
      "id": "SAT_4",
      "x": -4791.56103515625,
      "y": 4817.79296875,
      "z": 0.0
    },
    {
      "id": "SAT_5",
      "x": -4791.56103515625,
      "y": 4172.3310546875,
      "z": -2408.896484375
    }
  ],
  "edges": [
    {
      "source": 0,
      "target": 2,
      "distance": 6560.05078125,
      "rel_vel": 8.303439140319824,
      "attention": 0.4095601439476013
    },
    {
      "source": 0,
      "target": 3,
      "distance": 3144.428466796875,
      "rel_vel": 8.932025909423828,
      "attention": 0.7304775714874268
    },
    {
      "source": 0,
      "target": 4,
      "distance": 5473.2431640625,
      "rel_vel": 7.162153720855713,
      "attention": 0.45160526037216187
    },
    {
      "source": 1,
      "target": 2,
      "distance": 3232.740478515625,
      "rel_vel": 0.9861820936203003,
      "attention": 0.36707186698913574
    },
    {
      "source": 1,
      "target": 3,
      "distance": 5708.74267578125,
      "rel_vel": 5.995790958404541,
      "attention": 0.3791867792606354
    },
    {
      "source": 1,
      "target": 4,
      "distance": 4245.3974609375,
      "rel_vel": 7.22824239730835,
      "attention": 0.5598088502883911
    },
    {
      "source": 2,
      "target": 0,
      "distance": 6560.05078125,
      "rel_vel": 8.303439140319824,
      "attention": 0.4095601439476013
    },
    {
      "source": 2,
      "target": 1,
      "distance": 3232.740478515625,
      "rel_vel": 0.9861820936203003,
      "attention": 0.36707186698913574
    },
    {
      "source": 2,
      "target": 3,
      "distance": 6332.93603515625,
      "rel_vel": 6.866446495056152,
      "attention": 0.36467474699020386
    },
    {
      "source": 2,
      "target": 4,
      "distance": 6118.02001953125,
      "rel_vel": 8.049678802490234,
      "attention": 0.4360843896865845
    },
    {
      "source": 3,
      "target": 0,
      "distance": 3144.428466796875,
      "rel_vel": 8.932025909423828,
      "attention": 0.7304775714874268
    },
    {
      "source": 3,
      "target": 1,
      "distance": 5708.74267578125,
      "rel_vel": 5.995790958404541,
      "attention": 0.3791867792606354
    },
    {
      "source": 3,
      "target": 2,
      "distance": 6332.93603515625,
      "rel_vel": 6.866446495056152,
      "attention": 0.36467474699020386
    },
    {
      "source": 3,
      "target": 4,
      "distance": 2493.873291015625,
      "rel_vel": 2.8043484687805176,
      "attention": 0.511825680732727
    },
    {
      "source": 4,
      "target": 0,
      "distance": 5473.2431640625,
      "rel_vel": 7.162153720855713,
      "attention": 0.45160526037216187
    },
    {
      "source": 4,
      "target": 1,
      "distance": 4245.3974609375,
      "rel_vel": 7.22824239730835,
      "attention": 0.5598088502883911
    },
    {
      "source": 4,
      "target": 2,
      "distance": 6118.02001953125,
      "rel_vel": 8.049678802490234,
      "attention": 0.4360843896865845
    },
    {
      "source": 4,
      "target": 3,
      "distance": 2493.873291015625,
      "rel_vel": 2.8043484687805176,
      "attention": 0.511825680732727
    }
  ]
}