{
  "timestamp": "2025-04-15 15:58:02.375956+00:00",
  "nodes": [
    {
      "id": "SAT_1",
      "x": 2123.75244140625,
      "y": -4880.8916015625,
      "z": 4715.83251953125
    },
    {
      "id": "SAT_2",
      "x": 1705.6990966796875,
      "y": -7091.1025390625,
      "z": -220.9301300048828
    },
    {
      "id": "SAT_3",
      "x": 2465.580322265625,
      "y": -6892.716796875,
      "z": -1279.1524658203125
    },
    {
      "id": "SAT_4",
      "x": -2055.68896484375,
      "y": -6447.734375,
      "z": 0.0
    },
    {
      "id": "SAT_5",
      "x": -2055.68896484375,
      "y": -5583.90185546875,
      "z": 3223.8671875
    }
  ],
  "edges": [
    {
      "source": 0,
      "target": 1,
      "distance": 5425.07373046875,
      "rel_vel": 9.586038589477539,
      "attention": 0.25
    },
    {
      "source": 0,
      "target": 2,
      "distance": 6332.7822265625,
      "rel_vel": 7.977273941040039,
      "attention": 0.25
    }
  ]
}