{
  "timestamp": "2025-04-15 15:42:02.375956+00:00",
  "nodes": [
    {
      "id": "SAT_1",
      "x": -2667.699462890625,
      "y": -303.3301086425781,
      "z": 6585.125
    },
    {
      "id": "SAT_2",
      "x": -4290.88037109375,
      "y": -5173.1123046875,
      "z": -2840.635498046875
    },
    {
      "id": "SAT_3",
      "x": -4243.7197265625,
      "y": -5979.59912109375,
      "z": -1208.3472900390625
    },
    {
      "id": "SAT_4",
      "x": -6717.41943359375,
      "y": -1143.919921875,
      "z": 0.0
    },
    {
      "id": "SAT_5",
      "x": -6717.41943359375,
      "y": -990.6636962890625,
      "z": 571.9599609375
    }
  ],
  "edges": [
    {
      "source": 1,
      "target": 2,
      "distance": 1821.26611328125,
      "rel_vel": 2.756545066833496,
      "attention": 0.5329200029373169
    },
    {
      "source": 1,
      "target": 3,
      "distance": 5494.69677734375,
      "rel_vel": 4.818596839904785,
      "attention": 0.5002933740615845
    },
    {
      "source": 1,
      "target": 4,
      "distance": 5918.34228515625,
      "rel_vel": 4.558689594268799,
      "attention": 0.4537397027015686
    },
    {
      "source": 2,
      "target": 1,
      "distance": 1821.26611328125,
      "rel_vel": 2.756545066833496,
      "attention": 0.5329200029373169
    },
    {
      "source": 2,
      "target": 3,
      "distance": 5564.44873046875,
      "rel_vel": 5.91038703918457,
      "attention": 0.590173602104187
    },
    {
      "source": 2,
      "target": 4,
      "distance": 5846.208984375,
      "rel_vel": 6.978820323944092,
      "attention": 0.6659309267997742
    },
    {
      "source": 3,
      "target": 1,
      "distance": 5494.69677734375,
      "rel_vel": 4.818596839904785,
      "attention": 0.5002933740615845
    },
    {
      "source": 3,
      "target": 2,
      "distance": 5564.44873046875,
      "rel_vel": 5.91038703918457,
      "attention": 0.590173602104187
    },
    {
      "source": 3,
      "target": 4,
      "distance": 592.1365356445312,
      "rel_vel": 3.9587574005126953,
      "attention": 0.7065155506134033
    },
    {
      "source": 4,
      "target": 1,
      "distance": 5918.34228515625,
      "rel_vel": 4.558689594268799,
      "attention": 0.4537397027015686
    },
    {
      "source": 4,
      "target": 2,
      "distance": 5846.208984375,
      "rel_vel": 6.978820323944092,
      "attention": 0.6659309267997742
    },
    {
      "source": 4,
      "target": 3,
      "distance": 592.1365356445312,
      "rel_vel": 3.9587574005126953,
      "attention": 0.7065155506134033
    }
  ]
}