{
  "timestamp": "2025-04-15 15:26:32.375956+00:00",
  "nodes": [
    {
      "id": "SAT_1",
      "x": -4957.23388671875,
      "y": 4454.71435546875,
      "z": 2480.69677734375
    },
    {
      "id": "SAT_2",
      "x": -6559.1845703125,
      "y": 1046.00244140625,
      "z": -3020.75
    },
    {
      "id": "SAT_3",
      "x": -7422.4951171875,
      "y": -317.2998352050781,
      "z": -175.3620147705078
    },
    {
      "id": "SAT_4",
      "x": -4270.0966796875,
      "y": 5278.7900390625,
      "z": 0.0
    },
    {
      "id": "SAT_5",
      "x": -4270.0966796875,
      "y": 4571.56591796875,
      "z": -2639.39501953125
    }
  ],
  "edges": [
    {
      "source": 0,
      "target": 1,
      "distance": 6667.1943359375,
      "rel_vel": 8.780313491821289,
      "attention": 0.5963727235794067
    },
    {
      "source": 0,
      "target": 2,
      "distance": 5992.01806640625,
      "rel_vel": 8.763651847839355,
      "attention": 0.6338586211204529
    },
    {
      "source": 0,
      "target": 3,
      "distance": 2702.79736328125,
      "rel_vel": 9.124691009521484,
      "attention": 0.8455544710159302
    },
    {
      "source": 0,
      "target": 4,
      "distance": 5167.3154296875,
      "rel_vel": 7.486977577209473,
      "attention": 0.5970359444618225
    },
    {
      "source": 1,
      "target": 0,
      "distance": 6667.1943359375,
      "rel_vel": 8.780313491821289,
      "attention": 0.5963727235794067
    },
    {
      "source": 1,
      "target": 2,
      "distance": 3271.10546875,
      "rel_vel": 0.8847740888595581,
      "attention": 0.2712585926055908
    },
    {
      "source": 1,
      "target": 3,
      "distance": 5681.6669921875,
      "rel_vel": 6.166321277618408,
      "attention": 0.48080378770828247
    },
    {
      "source": 1,
      "target": 4,
      "distance": 4220.7763671875,
      "rel_vel": 7.334417819976807,
      "attention": 0.6410922408103943
    },
    {
      "source": 2,
      "target": 0,
      "distance": 5992.01806640625,
      "rel_vel": 8.763651847839355,
      "attention": 0.6338586211204529
    },
    {
      "source": 2,
      "target": 1,
      "distance": 3271.10546875,
      "rel_vel": 0.8847740888595581,
      "attention": 0.2712585926055908
    },
    {
      "source": 2,
      "target": 3,
      "distance": 6425.30810546875,
      "rel_vel": 6.950463771820068,
      "attention": 0.4898718297481537
    },
    {
      "source": 2,
      "target": 4,
      "distance": 6317.44287109375,
      "rel_vel": 8.010603904724121,
      "attention": 0.5657457709312439
    },
    {
      "source": 3,
      "target": 0,
      "distance": 2702.79736328125,
      "rel_vel": 9.124691009521484,
      "attention": 0.8455544710159302
    },
    {
      "source": 3,
      "target": 1,
      "distance": 5681.6669921875,
      "rel_vel": 6.166321277618408,
      "attention": 0.48080378770828247
    },
    {
      "source": 3,
      "target": 2,
      "distance": 6425.30810546875,
      "rel_vel": 6.950463771820068,
      "attention": 0.4898718297481537
    },
    {
      "source": 3,
      "target": 4,
      "distance": 2732.502685546875,
      "rel_vel": 2.4928832054138184,
      "attention": 0.40777820348739624
    },
    {
      "source": 4,
      "target": 0,
      "distance": 5167.3154296875,
      "rel_vel": 7.486977577209473,
      "attention": 0.5970359444618225
    },
    {
      "source": 4,
      "target": 1,
      "distance": 4220.7763671875,
      "rel_vel": 7.334417819976807,
      "attention": 0.6410922408103943
    },
    {
      "source": 4,
      "target": 2,
      "distance": 6317.44287109375,
      "rel_vel": 8.010603904724121,
      "attention": 0.5657457709312439
    },
    {
      "source": 4,
      "target": 3,
      "distance": 2732.502685546875,
      "rel_vel": 2.4928832054138184,
      "attention": 0.40777820348739624
    }
  ]
}