{
  "timestamp": "2025-04-15 15:48:02.375956+00:00",
  "nodes": [
    {
      "id": "SAT_1",
      "x": -931.8848876953125,
      "y": -2343.04736328125,
      "z": 6649.37744140625
    },
    {
      "id": "SAT_2",
      "x": -2229.254638671875,
      "y": -6635.8681640625,
      "z": -2058.551025390625
    },
    {
      "id": "SAT_3",
      "x": -1860.52392578125,
      "y": -7061.4248046875,
      "z": -1378.2589111328125
    },
    {
      "id": "SAT_4",
      "x": -5695.94140625,
      "y": -3721.4814453125,
      "z": 0.0
    },
    {
      "id": "SAT_5",
      "x": -5695.94140625,
      "y": -3222.8974609375,
      "z": 1860.74072265625
    }
  ],
  "edges": [
    {
      "source": 0,
      "target": 4,
      "distance": 6811.8583984375,
      "rel_vel": 4.481269836425781,
      "attention": 0.47035396099090576
    },
    {
      "source": 1,
      "target": 2,
      "distance": 883.0957641601562,
      "rel_vel": 3.1547625064849854,
      "attention": 0.6730926036834717
    },
    {
      "source": 1,
      "target": 3,
      "distance": 4974.8564453125,
      "rel_vel": 4.834020614624023,
      "attention": 0.6115039587020874
    },
    {
      "source": 1,
      "target": 4,
      "distance": 6247.169921875,
      "rel_vel": 3.40240740776062,
      "attention": 0.3919728100299835
    },
    {
      "source": 2,
      "target": 1,
      "distance": 883.0957641601562,
      "rel_vel": 3.1547625064849854,
      "attention": 0.6730926036834717
    },
    {
      "source": 2,
      "target": 3,
      "distance": 5269.2734375,
      "rel_vel": 5.4340949058532715,
      "attention": 0.656224250793457
    },
    {
      "source": 2,
      "target": 4,
      "distance": 6319.48046875,
      "rel_vel": 5.850183486938477,
      "attention": 0.6388868689537048
    },
    {
      "source": 3,
      "target": 1,
      "distance": 4974.8564453125,
      "rel_vel": 4.834020614624023,
      "attention": 0.6115039587020874
    },
    {
      "source": 3,
      "target": 2,
      "distance": 5269.2734375,
      "rel_vel": 5.4340949058532715,
      "attention": 0.656224250793457
    },
    {
      "source": 3,
      "target": 4,
      "distance": 1926.380615234375,
      "rel_vel": 3.345651149749756,
      "attention": 0.6330540776252747
    },
    {
      "source": 4,
      "target": 0,
      "distance": 6811.8583984375,
      "rel_vel": 4.481269836425781,
      "attention": 0.47035396099090576
    },
    {
      "source": 4,
      "target": 1,
      "distance": 6247.169921875,
      "rel_vel": 3.40240740776062,
      "attention": 0.3919728100299835
    },
    {
      "source": 4,
      "target": 2,
      "distance": 6319.48046875,
      "rel_vel": 5.850183486938477,
      "attention": 0.6388868689537048
    },
    {
      "source": 4,
      "target": 3,
      "distance": 1926.380615234375,
      "rel_vel": 3.345651149749756,
      "attention": 0.6330540776252747
    }
  ]
}